<?xml version='1.0' encoding='UTF-8'?>
<opponent>
    <tags>
        <tag>brunette</tag>
        <tag>medium_hair</tag>
        <tag>ahoge</tag>
        <tag>amber_eyes</tag>
        <tag>exotic_eyes</tag>
        <tag>fair-skinned</tag>
        <tag>pubic_hair</tag>
        <tag>medium_breasts</tag>
        <tag>school_uniform</tag>
        <tag>innocent</tag>
        <tag>kind</tag>
        <tag>moe</tag>
        <tag>shy</tag>
        <tag>boob_envy</tag>
        <tag>enf</tag>
        <tag>straight</tag>
        <tag>single</tag>
        <tag>japanese</tag>
        <tag>anime</tag>
        <tag>visual_novel</tag>
        <tag>clannad</tag>
        <tag>student</tag>
        <tag>butt_pose</tag>
        <tag>kneeling_forfeit</tag>
    </tags>
</opponent>
