<?xml version='1.0' encoding='UTF-8'?>
<metadata>
    <owner>zone-tan</owner>
    <noteworthy>
        <case name="Demon form Zone-tan" id="7" priority="Noteworthy" min="2" max="2">
            <description>After losing 3 times in a row, Zone-tan gets extremely angry and tranforms into her demon form.</description>
        </case>
        <case name="Zone-tan butt" id="8" priority="Noteworthy" min="3" max="3">
            <description>Zone-tan turns around and shows off her butt when she strips her panties.</description>
        </case>
    </noteworthy>
    <reviewed>true</reviewed>
    <hidden />
    <responses>
        <response id="1" opponent="raven" opponentId="8" />
        <response id="2" opponent="raven" opponentId="10" />
        <response id="3" opponent="leggy" opponentId="1" />
        <response id="4" opponent="nami" opponentId="10" />
        <response id="5" opponent="nami" opponentId="11" />
        <response id="6" opponent="nami" opponentId="9" />
        <response id="9" opponent="chihiro" opponentId="1" />
        <response id="10" opponent="chihiro" opponentId="2" />
        <response id="11" opponent="tharja" opponentId="11" />
        <response id="12" opponent="jessie" opponentId="20" />
    </responses>
    <notes />
    <labels>
        <label id="22" label="Ryuko classic" folder="" sort="0" />
        <label id="23" label="Panties collectible" folder="" sort="0" />
        <label id="24" label="Hentai Key collectible" folder="" sort="0" />
    </labels>
    <prefixes>
        <prefix>epi</prefix>
        <prefix>chair</prefix>
        <prefix>hand</prefix>
        <prefix>photo</prefix>
        <prefix>music</prefix>
        <prefix>wine</prefix>
        <prefix>wait</prefix>
        <prefix>maid</prefix>
        <prefix>restaurant</prefix>
        <prefix>room</prefix>
        <prefix>fan</prefix>
        <prefix>foot</prefix>
        <prefix>frame</prefix>
        <prefix>table</prefix>
        <prefix>menu</prefix>
        <prefix>candle</prefix>
        <prefix>hentai</prefix>
        <prefix>lemmy</prefix>
        <prefix>grain</prefix>
    </prefixes>
    <nextId>24</nextId>
    <markers>
        <marker scope="Public" name="" />
        <marker scope="Public" name="abcups" />
        <marker scope="Public" name="afstockings" />
        <marker scope="Public" name="akidearest">Aki, from the Youtube channel AkiDearest, is as much of a tentacle-lover as Zone-tan! They have collaborated a few times.</marker>
        <marker scope="Public" name="always_naked">Zone-tan prefers to be naked, even when she's recording ZTV News.</marker>
        <marker scope="Private" name="always_naked2" />
        <marker scope="Public" name="amaliamast" />
        <marker scope="Public" name="amaliamast2" />
        <marker scope="Public" name="angerissues" />
        <marker scope="Public" name="anime" />
        <marker scope="Public" name="backagain" />
        <marker scope="Public" name="bangbang" />
        <marker scope="Public" name="boobtease" />
        <marker scope="Public" name="booty-tan" />
        <marker scope="Public" name="calmingdown" />
        <marker scope="Public" name="calories" />
        <marker scope="Public" name="chansons" />
        <marker scope="Public" name="croixresearch" />
        <marker scope="Public" name="date_question" />
        <marker scope="Public" name="date_question_prompt" />
        <marker scope="Public" name="date_question2" />
        <marker scope="Public" name="elastic" />
        <marker scope="Private" name="f_your_a" />
        <marker scope="Public" name="femaleassholes" />
        <marker scope="Public" name="fuckingfe" />
        <marker scope="Public" name="fulldemon" />
        <marker scope="Public" name="fulldemonangry" />
        <marker scope="Public" name="fulldemonangrycool" />
        <marker scope="Public" name="fulldemonloss" />
        <marker scope="Public" name="fulldemonzone" />
        <marker scope="Public" name="furioushand" />
        <marker scope="Public" name="futaba_pro" />
        <marker scope="Public" name="futaba_pro2" />
        <marker scope="Public" name="futaba_tentacles" />
        <marker scope="Public" name="greetfap" />
        <marker scope="Public" name="greetintro" />
        <marker scope="Public" name="greetparodies" />
        <marker scope="Public" name="greetpervert" />
        <marker scope="Public" name="gwen_spiderman" />
        <marker scope="Public" name="heyamalia" />
        <marker scope="Public" name="heyamalia2" />
        <marker scope="Public" name="hifutaba" />
        <marker scope="Public" name="hugedicks" />
        <marker scope="Public" name="innocent" />
        <marker scope="Public" name="jessiebackdoor" />
        <marker scope="Public" name="jessiecommission" />
        <marker scope="Public" name="jessiekyat" />
        <marker scope="Public" name="jessielies" />
        <marker scope="Public" name="jessielights" />
        <marker scope="Public" name="jessiemasturbate" />
        <marker scope="Public" name="jessieopen" />
        <marker scope="Public" name="jessieporn" />
        <marker scope="Public" name="jessiesexnumber" />
        <marker scope="Public" name="jessiesexposition" />
        <marker scope="Public" name="jessiesmoker" />
        <marker scope="Public" name="jin_jura" />
        <marker scope="Public" name="joining" />
        <marker scope="Public" name="jurihentai" />
        <marker scope="Public" name="jurihide" />
        <marker scope="Public" name="justonedance" />
        <marker scope="Public" name="justonedance2" />
        <marker scope="Public" name="kaminacum" />
        <marker scope="Public" name="kaminacum2" />
        <marker scope="Public" name="kissmark" />
        <marker scope="Private" name="korra_spirit_portals" />
        <marker scope="Public" name="kyuwatching" />
        <marker scope="Public" name="kyuwatching2" />
        <marker scope="Public" name="likes_to_sing" />
        <marker scope="Public" name="long_and_messy" />
        <marker scope="Public" name="madeforit" />
        <marker scope="Public" name="mahiru_catchphrase" />
        <marker scope="Public" name="mahiruselfie" />
        <marker scope="Public" name="manlyman" />
        <marker scope="Public" name="maybepenis" />
        <marker scope="Public" name="meetnfuck" />
        <marker scope="Public" name="meia_collect" />
        <marker scope="Public" name="meia_obscure" />
        <marker scope="Private" name="mirror" />
        <marker scope="Private" name="mirror2" />
        <marker scope="Private" name="next_to_you" />
        <marker scope="Public" name="nonutnovember" />
        <marker scope="Public" name="overwatching" />
        <marker scope="Public" name="palutena_religion" />
        <marker scope="Public" name="patreon" />
        <marker scope="Public" name="pico_day">Pico Day is a yearly anniversary on NewGrounds, celebrating NewGrounds' past and its mascots, especially Pico.</marker>
        <marker scope="Public" name="pincreampie" />
        <marker scope="Public" name="playerreward" />
        <marker scope="Public" name="poker_strats">Zone-tan has played a ton of strip poker in the past, so she has some great poker skills.</marker>
        <marker scope="Public" name="questionable_decisions">Zone-tan even admits herself that she hasn't lead quite an innocent life...</marker>
        <marker scope="Public" name="raven_copy_hair" />
        <marker scope="Public" name="raven_hide_face">Raven is hiding her face, and Zone-tan doesn't like that at all.</marker>
        <marker scope="Public" name="raven_long_hair" />
        <marker scope="Public" name="raven_regret" />
        <marker scope="Public" name="ravendownthere" />
        <marker scope="Public" name="ryukoflash" />
        <marker scope="Public" name="ryukomeet" />
        <marker scope="Public" name="ryukosplay" />
        <marker scope="Public" name="sausage" />
        <marker scope="Public" name="seinal" />
        <marker scope="Public" name="shad_gwen" />
        <marker scope="Public" name="shampoo">Zone-tan wants the player to stop jacking off with shampoo... because it's weird...</marker>
        <marker scope="Public" name="sittingdown" />
        <marker scope="Public" name="slowburn" />
        <marker scope="Private" name="social_media" />
        <marker scope="Public" name="sonya_commando" />
        <marker scope="Public" name="sonya_twilight" />
        <marker scope="Public" name="specialeyes" />
        <marker scope="Public" name="starfirebestgirl" />
        <marker scope="Public" name="strangled" />
        <marker scope="Public" name="strangled2" />
        <marker scope="Public" name="tentaclehack" />
        <marker scope="Public" name="tentaclehack2" />
        <marker scope="Public" name="tentacles">Zone-tan loves her tentacles! Her sidekick is Lemmy, a green tentacle monster.</marker>
        <marker scope="Public" name="terrabestgirl" />
        <marker scope="Private" name="thank_you_anyway" />
        <marker scope="Public" name="top5" />
        <marker scope="Public" name="touch" />
        <marker scope="Public" name="translucent_dildo">Zone-tan makes a comment about how much she loves translucent dildos, since they let you see everything that's going on. She used a translucent dildo in her 'leaked sex tape' video.</marker>
        <marker scope="Private" name="translucent_dildo2" />
        <marker scope="Public" name="turnbased" />
        <marker scope="Public" name="valentine_reward" />
        <marker scope="Public" name="watching_futaba" />
        <marker scope="Public" name="weiss_daddy_issues" />
        <marker scope="Public" name="youtubetos" />
        <marker scope="Public" name="zone_egg" />
        <marker scope="Public" name="zone_victims" />
        <marker scope="Public" name="zonegreet" />
        <marker scope="Public" name="zone-sama">Zone-sama is the founder and main animator of ZONE and the ZONE-Archive. He created Zone-tan.</marker>
        <marker scope="Private" name="zone-tan_angry" />
        <marker scope="Private" name="zone-tan_angry2" />
        <marker scope="Public" name="zone-tan_deciding">Zone-tan is deciding which one of her opponents she wants to put in ZONE's next flash video.</marker>
        <marker scope="Private" name="zone-tan_deciding2" />
        <marker scope="Public" name="zone-tan_fap_song">Zone-tan's first song: https://www.youtube.com/watch?v=QEPHLPmt914</marker>
        <marker scope="Public" name="zone-tan_fap_song_alt" />
        <marker scope="Public" name="zone-tan_fap_song_alt2" />
        <marker scope="Private" name="zone-tan_fap_song2" />
        <marker scope="Public" name="zone-tan_hamburgers">Zone-tan just really loves hamburgers.</marker>
        <marker scope="Private" name="zone-tan_hamburgers2" />
        <marker scope="Private" name="zone-tan_likes_singing" />
        <marker scope="Private" name="zone-tan_likes_singing2" />
        <marker scope="Public" name="zone-tan_love_song">Zone-tan's second song: https://www.youtube.com/watch?v=Nvs89HejVjE</marker>
        <marker scope="Private" name="zone-tan_love_song_alt" />
        <marker scope="Private" name="zone-tan_love_song_alt2" />
        <marker scope="Private" name="zone-tan_love_song2" />
        <marker scope="Public" name="zone-tan_singing">Zone-tan sometimes hums or sings a portion of one of her two songs.</marker>
        <marker scope="Private" name="zone-tan-singing" />
        <marker scope="Public" name="zt_fapsong" />
        <marker scope="Public" name="zt_problem" />
        <marker scope="Public" name="zt_sing" />
        <marker scope="Public" name="zt_song" />
        <marker scope="Public" name="zt_songdance" />
        <marker scope="Public" name="zt_songfap" />
        <marker scope="Public" name="zt_songlove" />
        <marker scope="Public" name="zt_songporn" />
        <marker scope="Public" name="zt_songtitans" />
    </markers>
    <recipes />
</metadata>
