<?xml version='1.0' encoding='UTF-8'?>
<metadata>
    <owner>spooky</owner>
    <noteworthy>
        <case name="Knives count?" id="1" priority="FYI" min="1" max="1">
            <description>Spooky uses her knife as a buffer because she came to the game only wearing a dress.</description>
        </case>
        <case name="Seriously, just a dress." id="2" priority="Noteworthy" min="2" max="2">
            <description>After removing her dress, Spooky is breifly nude before then apparating underwear.</description>
        </case>
    </noteworthy>
    <hidden />
    <responses>
        <response id="3" opponent="sakura" opponentId="2" />
        <response id="4" opponent="sakura" opponentId="3" />
        <response id="5" opponent="saki_zls" opponentId="1" />
        <response id="8" opponent="saki_zls" opponentId="3" />
    </responses>
    <notes />
    <labels />
    <prefixes />
    <nextId>8</nextId>
    <markers>
        <marker scope="Public" name="" />
        <marker scope="Public" name="1v1" />
        <marker scope="Public" name="MeiaRules" />
        <marker scope="Public" name="showsomeskin" />
        <marker scope="Public" name="SpookyWinning" />
        <marker scope="Public" name="SpookyWinning1" />
        <marker scope="Public" name="ZLS1" />
        <marker scope="Public" name="ZLS2" />
    </markers>
</metadata>
