<?xml version='1.0' encoding='UTF-8'?>
<opponent>
    <lastupdate>1669351030179</lastupdate>
    <enabled>true</enabled>
    <first>Adrien</first>
    <last>Agreste</last>
    <label>Cat Noir</label>
    <pic>0-confident.png</pic>
    <gender>male</gender>
    <from>Miraculous: Tales of Ladybug and Cat Noir</from>
    <writer>nmasp</writer>
    <artist>TheLonelyPhonebox</artist>
    <description>Adrien, a fashion model by day, and Cat Noir, daring hero by night, he forms one half of the superhero team that protects Paris from the evil Hawk Moth. </description>
    <layers>8</layers>
    <has_collectibles>false</has_collectibles>
    <lines>4153</lines>
    <poses>220</poses>
</opponent>
