<?xml version='1.0' encoding='UTF-8'?>
<opponent>
    <lastupdate>1649863583507</lastupdate>
    <enabled>false</enabled>
    <first>Mari</first>
    <last>Setogaya</last>
    <label>Mari</label>
    <pic>0-calm.png</pic>
    <gender>female</gender>
    <height />
    <from>Itadaki Seieki</from>
    <writer>Mymans76</writer>
    <artist>MyMainAccIsANord, Mymans76</artist>
    <description>The lovely half-vampire, half-succubus from the erotic manga/anime Itadaki Seieki. This version of her never met Kanzaki-Kun, so she's not in any relationship.</description>
    <layers>6</layers>
    <has_collectibles>true</has_collectibles>
    <lines>1782</lines>
    <poses>376</poses>
</opponent>
